{
  "for": "executeautomation/mcp-playwright",
  "slug": "executeautomation__mcp-playwright",
  "of_capabilities": [
    "web"
  ],
  "alternatives": [
    {
      "repo": "microsoft/playwright-mcp",
      "slug": "microsoft__playwright-mcp",
      "composite": 100,
      "axes": {
        "reliability": 100,
        "documentation": 100,
        "trust": 100,
        "community": 100
      },
      "kind": "server",
      "subkind": "integration",
      "capabilities": [
        "web",
        "ai",
        "devtools"
      ],
      "stars": 31575,
      "language": "TypeScript",
      "url": "https://github.com/microsoft/playwright-mcp",
      "detail_url": "/servers/microsoft__playwright-mcp.json",
      "similarity": 0.333,
      "shared_capabilities": [
        "web"
      ]
    }
  ]
}